MANIFEST.in
README.rst
setup.py
czml/__init__.py
czml/czml.py
czml/test_main.py
czml/utils.py
czml.egg-info/PKG-INFO
czml.egg-info/SOURCES.txt
czml.egg-info/dependency_links.txt
czml.egg-info/entry_points.txt
czml.egg-info/not-zip-safe
czml.egg-info/requires.txt
czml.egg-info/top_level.txt
docs/HISTORY.txt
docs/LICENSE.LGPL
docs/LICENSE.txt