Metadata-Version: 1.1
Name: czml
Version: 0.3.2
Summary: Read and write CZML in Python
Home-page: https://github.com/cleder/czml
Author: Christian Ledermann
Author-email: christian.ledermann@gmail.com
License: LGPL
Keywords: GIS JOSN CZML Cesium Globe
Platform: UNKNOWN
Classifier: Topic :: Scientific/Engineering :: GIS
Classifier: Programming Language :: Python
Classifier: Programming Language :: Python :: 2.7
Classifier: Programming Language :: Python :: 3.3
Classifier: Programming Language :: Python :: 3.4
Classifier: Intended Audience :: Developers
Classifier: License :: OSI Approved :: GNU Library or Lesser General Public License (LGPL)
Classifier: Development Status :: 4 - Beta
Classifier: Operating System :: OS Independent
